{
    "usage": [
        {
            "id": "cjc6t4kpa0000zmop1x1ozb5i",
            "date": "Mon Jan 08 2018 16:57:05 GMT-0600 (CST)",
            "browser": "Mozilla/5.0 (Macintosh; Intel Mac OS X 10_13_0) AppleWebKit/537.36 (KHTML, like Gecko) Chrome/63.0.3239.84 Safari/537.36",
            "clientIp": "::1",
            "method": "POST",
            "url": "/api/profile/login",
            "error": {
                "code": "auth/user-not-found",
                "message": "There is no user record corresponding to this identifier. The user may have been deleted."
            },
            "success": false,
            "responseTime": 434
        },
        {
            "id": "cjc6t8ziw0001zmopxsowxmis",
            "date": "Mon Jan 08 2018 17:00:31 GMT-0600 (CST)",
            "browser": "Mozilla/5.0 (Macintosh; Intel Mac OS X 10_13_0) AppleWebKit/537.36 (KHTML, like Gecko) Chrome/63.0.3239.84 Safari/537.36",
            "clientIp": "::1",
            "method": "POST",
            "url": "/api/profile/login",
            "error": {
                "code": "auth/user-not-found",
                "message": "There is no user record corresponding to this identifier. The user may have been deleted."
            },
            "success": false,
            "responseTime": 255
        },
        {
            "id": "cjc74phl10002zmopvq7x2u0x",
            "date": "Mon Jan 08 2018 22:21:16 GMT-0600 (CST)",
            "browser": "Mozilla/5.0 (Macintosh; Intel Mac OS X 10_13_0) AppleWebKit/537.36 (KHTML, like Gecko) Chrome/63.0.3239.84 Safari/537.36",
            "clientIp": "::1",
            "method": "POST",
            "url": "/api/profile/login",
            "error": {
                "code": "auth/user-not-found",
                "message": "There is no user record corresponding to this identifier. The user may have been deleted."
            },
            "success": false,
            "responseTime": 1010
        },
        {
            "id": "cjc74qosc0003zmop6u7p542e",
            "date": "Mon Jan 08 2018 22:22:12 GMT-0600 (CST)",
            "browser": "Mozilla/5.0 (Macintosh; Intel Mac OS X 10_13_0) AppleWebKit/537.36 (KHTML, like Gecko) Chrome/63.0.3239.84 Safari/537.36",
            "clientIp": "::1",
            "method": "POST",
            "url": "/api/profile/login",
            "error": false,
            "success": true,
            "responseTime": 1388
        },
        {
            "id": "cjc74r5ym0004zmopc2pb0bmd",
            "date": "Mon Jan 08 2018 22:22:34 GMT-0600 (CST)",
            "browser": "Mozilla/5.0 (Macintosh; Intel Mac OS X 10_13_0) AppleWebKit/537.36 (KHTML, like Gecko) Chrome/63.0.3239.84 Safari/537.36",
            "clientIp": "::1",
            "method": "POST",
            "url": "/api/profile/login",
            "error": {
                "code": "auth/wrong-password",
                "message": "The password is invalid or the user does not have a password."
            },
            "success": false,
            "responseTime": 1247
        },
        {
            "id": "cjc74rgl70005zmop8g9t4f2h",
            "date": "Mon Jan 08 2018 22:22:48 GMT-0600 (CST)",
            "browser": "Mozilla/5.0 (Macintosh; Intel Mac OS X 10_13_0) AppleWebKit/537.36 (KHTML, like Gecko) Chrome/63.0.3239.84 Safari/537.36",
            "clientIp": "::1",
            "method": "POST",
            "url": "/api/profile/login",
            "error": {
                "code": "auth/wrong-password",
                "message": "The password is invalid or the user does not have a password."
            },
            "success": false,
            "responseTime": 1005
        },
        {
            "id": "cjc74rhpp0006zmop3agvz24a",
            "date": "Mon Jan 08 2018 22:22:50 GMT-0600 (CST)",
            "browser": "Mozilla/5.0 (Macintosh; Intel Mac OS X 10_13_0) AppleWebKit/537.36 (KHTML, like Gecko) Chrome/63.0.3239.84 Safari/537.36",
            "clientIp": "::1",
            "method": "POST",
            "url": "/api/profile/login",
            "error": {
                "code": "auth/wrong-password",
                "message": "The password is invalid or the user does not have a password."
            },
            "success": false,
            "responseTime": 502
        },
        {
            "id": "cjc74rihz0007zmop7xwoo2sl",
            "date": "Mon Jan 08 2018 22:22:51 GMT-0600 (CST)",
            "browser": "Mozilla/5.0 (Macintosh; Intel Mac OS X 10_13_0) AppleWebKit/537.36 (KHTML, like Gecko) Chrome/63.0.3239.84 Safari/537.36",
            "clientIp": "::1",
            "method": "POST",
            "url": "/api/profile/login",
            "error": {
                "code": "auth/wrong-password",
                "message": "The password is invalid or the user does not have a password."
            },
            "success": false,
            "responseTime": 508
        },
        {
            "id": "cjc74rjgx0008zmop9y5uy23u",
            "date": "Mon Jan 08 2018 22:22:52 GMT-0600 (CST)",
            "browser": "Mozilla/5.0 (Macintosh; Intel Mac OS X 10_13_0) AppleWebKit/537.36 (KHTML, like Gecko) Chrome/63.0.3239.84 Safari/537.36",
            "clientIp": "::1",
            "method": "POST",
            "url": "/api/profile/login",
            "error": {
                "code": "auth/wrong-password",
                "message": "The password is invalid or the user does not have a password."
            },
            "success": false,
            "responseTime": 784
        },
        {
            "id": "cjc74rqnd0009zmop53yp2wsd",
            "date": "Mon Jan 08 2018 22:23:01 GMT-0600 (CST)",
            "browser": "Mozilla/5.0 (Macintosh; Intel Mac OS X 10_13_0) AppleWebKit/537.36 (KHTML, like Gecko) Chrome/63.0.3239.84 Safari/537.36",
            "clientIp": "::1",
            "method": "POST",
            "url": "/api/profile/login",
            "error": {
                "code": "auth/wrong-password",
                "message": "The password is invalid or the user does not have a password."
            },
            "success": false,
            "responseTime": 1056
        },
        {
            "id": "cjc74rru9000azmop2oe0lro5",
            "date": "Mon Jan 08 2018 22:23:03 GMT-0600 (CST)",
            "browser": "Mozilla/5.0 (Macintosh; Intel Mac OS X 10_13_0) AppleWebKit/537.36 (KHTML, like Gecko) Chrome/63.0.3239.84 Safari/537.36",
            "clientIp": "::1",
            "method": "POST",
            "url": "/api/profile/login",
            "error": {
                "code": "auth/too-many-requests",
                "message": "We have blocked all requests from this device due to unusual activity. Try again later."
            },
            "success": false,
            "responseTime": 594
        },
        {
            "id": "cjc74s596000bzmopf0rodsug",
            "date": "Mon Jan 08 2018 22:23:20 GMT-0600 (CST)",
            "browser": "Mozilla/5.0 (Macintosh; Intel Mac OS X 10_13_0) AppleWebKit/537.36 (KHTML, like Gecko) Chrome/63.0.3239.84 Safari/537.36",
            "clientIp": "::1",
            "method": "POST",
            "url": "/api/profile/login",
            "error": {
                "code": "auth/wrong-password",
                "message": "The password is invalid or the user does not have a password."
            },
            "success": false,
            "responseTime": 987
        },
        {
            "id": "cjc74vjwj000czmopfwn5eahi",
            "date": "Mon Jan 08 2018 22:25:59 GMT-0600 (CST)",
            "browser": "Mozilla/5.0 (Macintosh; Intel Mac OS X 10_13_0) AppleWebKit/537.36 (KHTML, like Gecko) Chrome/63.0.3239.84 Safari/537.36",
            "clientIp": "::1",
            "method": "POST",
            "url": "/api/profile/login",
            "error": {
                "code": "auth/wrong-password",
                "message": "The password is invalid or the user does not have a password."
            },
            "success": false,
            "responseTime": 951
        },
        {
            "id": "cjc74vnre000dzmopg98s0hqn",
            "date": "Mon Jan 08 2018 22:26:04 GMT-0600 (CST)",
            "browser": "Mozilla/5.0 (Macintosh; Intel Mac OS X 10_13_0) AppleWebKit/537.36 (KHTML, like Gecko) Chrome/63.0.3239.84 Safari/537.36",
            "clientIp": "::1",
            "method": "POST",
            "url": "/api/profile/login",
            "error": {
                "code": "auth/too-many-requests",
                "message": "We have blocked all requests from this device due to unusual activity. Try again later."
            },
            "success": false,
            "responseTime": 918
        },
        {
            "id": "cjc74w1uj000ezmoprk4r4tpg",
            "date": "Mon Jan 08 2018 22:26:22 GMT-0600 (CST)",
            "browser": "Mozilla/5.0 (Macintosh; Intel Mac OS X 10_13_0) AppleWebKit/537.36 (KHTML, like Gecko) Chrome/63.0.3239.84 Safari/537.36",
            "clientIp": "::1",
            "method": "POST",
            "url": "/api/profile/login",
            "error": false,
            "success": true,
            "responseTime": 1522
        },
        {
            "id": "cjc752ra2000fzmoprufylepj",
            "date": "Mon Jan 08 2018 22:31:35 GMT-0600 (CST)",
            "browser": "Mozilla/5.0 (Macintosh; Intel Mac OS X 10_13_0) AppleWebKit/537.36 (KHTML, like Gecko) Chrome/63.0.3239.84 Safari/537.36",
            "clientIp": "::1",
            "method": "POST",
            "url": "/api/profile/login",
            "error": false,
            "success": true,
            "responseTime": 1505
        },
        {
            "id": "cjc754piq000gzmopxpba7ze5",
            "date": "Mon Jan 08 2018 22:33:06 GMT-0600 (CST)",
            "browser": "Mozilla/5.0 (Macintosh; Intel Mac OS X 10_13_0) AppleWebKit/537.36 (KHTML, like Gecko) Chrome/63.0.3239.84 Safari/537.36",
            "clientIp": "::1",
            "method": "POST",
            "url": "/api/profile",
            "error": false,
            "success": true,
            "responseTime": 3302
        },
        {
            "id": "cjc755cox000hzmopnmk0c40t",
            "date": "Mon Jan 08 2018 22:33:36 GMT-0600 (CST)",
            "browser": "Mozilla/5.0 (Macintosh; Intel Mac OS X 10_13_0) AppleWebKit/537.36 (KHTML, like Gecko) Chrome/63.0.3239.84 Safari/537.36",
            "clientIp": "::1",
            "method": "POST",
            "url": "/api/profile/login",
            "error": false,
            "success": true,
            "responseTime": 1489
        },
        {
            "id": "cjc757l31000izmoppv27ehbo",
            "date": "Mon Jan 08 2018 22:35:21 GMT-0600 (CST)",
            "browser": "Mozilla/5.0 (Macintosh; Intel Mac OS X 10_13_0) AppleWebKit/537.36 (KHTML, like Gecko) Chrome/63.0.3239.84 Safari/537.36",
            "clientIp": "::1",
            "method": "POST",
            "url": "/api/profile/login",
            "error": false,
            "success": true,
            "responseTime": 1371
        },
        {
            "id": "cjc75ausk000jzmop0465dz7r",
            "date": "Mon Jan 08 2018 22:37:53 GMT-0600 (CST)",
            "browser": "Mozilla/5.0 (Macintosh; Intel Mac OS X 10_13_0) AppleWebKit/537.36 (KHTML, like Gecko) Chrome/63.0.3239.84 Safari/537.36",
            "clientIp": "::1",
            "method": "POST",
            "url": "/api/profile/login",
            "error": false,
            "success": true,
            "responseTime": 1343
        },
        {
            "id": "cjc75fbmw000kzmopetknvdix",
            "date": "Mon Jan 08 2018 22:41:22 GMT-0600 (CST)",
            "browser": "Mozilla/5.0 (Macintosh; Intel Mac OS X 10_13_0) AppleWebKit/537.36 (KHTML, like Gecko) Chrome/63.0.3239.84 Safari/537.36",
            "clientIp": "::1",
            "method": "POST",
            "url": "/api/profile/login",
            "error": false,
            "success": true,
            "responseTime": 723
        },
        {
            "id": "cjc75j1uf000lzmopwbcataip",
            "date": "Mon Jan 08 2018 22:44:16 GMT-0600 (CST)",
            "browser": "Mozilla/5.0 (Macintosh; Intel Mac OS X 10_13_0) AppleWebKit/537.36 (KHTML, like Gecko) Chrome/63.0.3239.84 Safari/537.36",
            "clientIp": "::1",
            "method": "POST",
            "url": "/api/profile/login",
            "error": false,
            "success": true,
            "responseTime": 598
        },
        {
            "id": "cjc75or76000mzmopslu4ryug",
            "date": "Mon Jan 08 2018 22:48:42 GMT-0600 (CST)",
            "browser": "Mozilla/5.0 (Macintosh; Intel Mac OS X 10_13_0) AppleWebKit/537.36 (KHTML, like Gecko) Chrome/63.0.3239.84 Safari/537.36",
            "clientIp": "::1",
            "method": "POST",
            "url": "/api/profile/login",
            "error": false,
            "success": true,
            "responseTime": 796
        },
        {
            "id": "cjc75q79v000nzmopzjzizwmv",
            "date": "Mon Jan 08 2018 22:49:49 GMT-0600 (CST)",
            "browser": "Mozilla/5.0 (Macintosh; Intel Mac OS X 10_13_0) AppleWebKit/537.36 (KHTML, like Gecko) Chrome/63.0.3239.84 Safari/537.36",
            "clientIp": "::1",
            "method": "POST",
            "url": "/api/profile/login",
            "error": false,
            "success": true,
            "responseTime": 1274
        }
    ]
}